./.gitignore
./.python-version
./MANIFEST.in
./PKG-INFO
./README.md
./__init__.py
./deployx.example.yml
./install.sh
./main.py
./pyproject.toml
./uninstall.sh
./uv.lock
./.github/workflows/publish.yml
./cli/__init__.py
./cli/base.py
./cli/commands.py
./cli/factory.py
./commands/__init__.py
./commands/config.py
./commands/deploy.py
./commands/env_config.py
./commands/history.py
./commands/init.py
./commands/init_helpers.py
./commands/init_utils.py
./commands/interactive.py
./commands/logs.py
./commands/platform_config.py
./commands/rollback.py
./commands/status.py
./core/__init__.py
./core/constants.py
./core/logging.py
./core/models.py
./core/services.py
./detectors/__init__.py
./detectors/project.py
./platforms/__init__.py
./platforms/base.py
./platforms/env_interface.py
./platforms/factory.py
./platforms/github.py
./platforms/netlify.py
./platforms/railway.py
./platforms/vercel.py
./platforms/render/__init__.py
./platforms/render/api.py
./platforms/render/detector.py
./platforms/render/platform.py
./tests/__init__.py
./tests/run_all_tests.py
./tests/test_config.py
./tests/test_deploy_command.py
./tests/test_detection.py
./tests/test_github_platform.py
./tests/test_integration.py
./tests/test_manual_scenarios.py
./tests/test_platforms.py
./tests/test_project_detection.py
./utils/__init__.py
./utils/config.py
./utils/env_manager.py
./utils/environment.py
./utils/errors.py
./utils/ui.py
./utils/validator.py
deployx-0.7.0.dist-info/METADATA
deployx-0.7.0.dist-info/WHEEL
deployx-0.7.0.dist-info/entry_points.txt
deployx-0.7.0.dist-info/RECORD
