Metadata-Version: 2.4
Name: deployx
Version: 0.7.0
Summary: One CLI for all your deployments, stop memorizing platform-specific commands
Project-URL: Homepage, https://github.com/Adelodunpeter25/deployx
Project-URL: Documentation, https://github.com/Adelodunpeter25/deployx#readme
Project-URL: Repository, https://github.com/Adelodunpeter25/deployx.git
Project-URL: Bug Tracker, https://github.com/Adelodunpeter25/deployx/issues
Author-email: Adelodun Peter <adelodunpeter24@gmail.com>
Maintainer-email: Adelodun Peter <adelodunpeter24@gmail.com>
License: MIT
Keywords: cli,deployment,github-pages,netlify,productivity,render,vercel,web
Classifier: Development Status :: 4 - Beta
Classifier: Environment :: Console
Classifier: Intended Audience :: Developers
Classifier: License :: OSI Approved :: MIT License
Classifier: Operating System :: OS Independent
Classifier: Programming Language :: Python :: 3
Classifier: Programming Language :: Python :: 3.9
Classifier: Programming Language :: Python :: 3.10
Classifier: Programming Language :: Python :: 3.11
Classifier: Programming Language :: Python :: 3.12
Classifier: Topic :: Internet :: WWW/HTTP :: Site Management
Classifier: Topic :: Software Development :: Build Tools
Classifier: Topic :: System :: Installation/Setup
Classifier: Topic :: Utilities
Requires-Python: >=3.9
Requires-Dist: click>=8.1.8
Requires-Dist: gitpython>=3.1.45
Requires-Dist: pydantic>=2.0.0
Requires-Dist: pygithub>=2.8.1
Requires-Dist: pyyaml>=6.0.3
Requires-Dist: questionary>=2.1.1
Requires-Dist: requests>=2.32.5
Requires-Dist: rich>=14.2.0
Provides-Extra: dev
Requires-Dist: black>=23.0.0; extra == 'dev'
Requires-Dist: mypy>=1.0.0; extra == 'dev'
Requires-Dist: pytest-cov>=4.0.0; extra == 'dev'
Requires-Dist: pytest>=7.0.0; extra == 'dev'
Requires-Dist: ruff>=0.1.0; extra == 'dev'
